grocy_telegram_bot/__init__.py
grocy_telegram_bot/cache.py
grocy_telegram_bot/config.py
grocy_telegram_bot/const.py
grocy_telegram_bot/main.py
grocy_telegram_bot/notifier.py
grocy_telegram_bot/permissions.py
grocy_telegram_bot/stats.py
grocy_telegram_bot/telegram_util.py
grocy_telegram_bot/util.py
grocy_telegram_bot/bot/__init__.py
grocy_telegram_bot/bot/inline_keyboard_handler.py
grocy_telegram_bot/bot/reply_keyboard_handler.py
grocy_telegram_bot/commands/__init__.py
grocy_telegram_bot/commands/chore.py
grocy_telegram_bot/commands/config.py
grocy_telegram_bot/commands/help.py
grocy_telegram_bot/commands/inventory.py
grocy_telegram_bot/commands/shopping_list.py
grocy_telegram_bot/commands/stats.py
grocy_telegram_bot/commands/version.py
grocy_telegram_bot/monitoring/__init__.py
grocy_telegram_bot/monitoring/monitor.py
grocy_telegram_bot/monitoring/watcher/__init__.py
grocy_telegram_bot/monitoring/watcher/chore.py
grocy_telegram_bot/monitoring/watcher/inventory.py
grocy_telegram_bot/monitoring/watcher/shopping_list.py
grocy_telegram_bot/monitoring/watcher/task.py
tests/__init__.py
tests/fuzzy_match_test.py
tests/minifiable_data_test.py
tests/monitor_test.py
grocy_telegram_bot-1.0.0.dist-info/LICENSE
grocy_telegram_bot-1.0.0.dist-info/METADATA
grocy_telegram_bot-1.0.0.dist-info/WHEEL
grocy_telegram_bot-1.0.0.dist-info/entry_points.txt
grocy_telegram_bot-1.0.0.dist-info/top_level.txt
grocy_telegram_bot-1.0.0.dist-info/RECORD
