Metadata-Version: 2.1
Name: grocy-telegram-bot
Version: 1.0.0
Summary: A telegram bot to interact with grocy
Home-page: https://github.com/markusressel/grocy-telegram-bot
Author: Markus Ressel
Author-email: mail@markusressel.de
License: AGPLv3+
Platform: UNKNOWN
Classifier: Development Status :: 5 - Production/Stable
Classifier: License :: OSI Approved :: GNU General Public License v3 or later (GPLv3+)
Classifier: Programming Language :: Python :: 3
Classifier: Programming Language :: Python :: 3.6
Classifier: Programming Language :: Python :: 3.7
Classifier: Programming Language :: Python :: 3.8
Requires-Dist: babel (==2.8.0)
Requires-Dist: certifi (==2019.11.28)
Requires-Dist: cffi (==1.14.0)
Requires-Dist: chardet (==3.0.4)
Requires-Dist: container-app-conf (==5.0.0)
Requires-Dist: cryptography (==2.8)
Requires-Dist: decorator (==4.4.2)
Requires-Dist: emoji (==0.5.4)
Requires-Dist: expiringdict (==1.2.0)
Requires-Dist: future (==0.18.2)
Requires-Dist: fuzzywuzzy (==0.18.0)
Requires-Dist: idna (==2.9)
Requires-Dist: iso8601 (==0.1.12)
Requires-Dist: prometheus-client (==0.7.1)
Requires-Dist: py-range-parse (==1.0.5)
Requires-Dist: pycparser (==2.20)
Requires-Dist: pygrocy (==0.13.0)
Requires-Dist: python-dateutil (==2.8.1)
Requires-Dist: python-levenshtein (==0.12.0)
Requires-Dist: python-telegram-bot (==12.4.2)
Requires-Dist: pytimeparse (==1.1.8)
Requires-Dist: pytz (==2019.3)
Requires-Dist: requests (==2.23.0)
Requires-Dist: ruamel.yaml (==0.16.10)
Requires-Dist: ruamel.yaml.clib (==0.2.0)
Requires-Dist: six (==1.14.0)
Requires-Dist: telegram-click (==3.3.4)
Requires-Dist: toml (==0.10.0)
Requires-Dist: tornado (==6.0.4)
Requires-Dist: typing (==3.7.4.1)
Requires-Dist: tzlocal (==2.0.0)
Requires-Dist: urllib3 (==1.25.8)
